pyflind/__init__.py
pyflind/bidirmap.py
pyflind/codec.py
pyflind/device.py
pyflind/deviceio.py
pyflind/group.py
pyflind/recording.py
pyflind/smx00.py
pyflind/smx00_cli.py
pyflind/util.py
pyflind-0.2.3.dist-info/licenses/LICENSE
pyflind-0.2.3.dist-info/METADATA
pyflind-0.2.3.dist-info/WHEEL
pyflind-0.2.3.dist-info/entry_points.txt
pyflind-0.2.3.dist-info/top_level.txt
pyflind-0.2.3.dist-info/RECORD
