Metadata-Version: 2.4
Name: pyflind
Version: 0.2.3
Summary: A python library for FieldLine Industries products
Author-email: Matt Liss <matt@fieldlineindustries.com>, Ezra Godfrey <eg@fieldlineinc.com>, Andreas Griesshammer <ag@fieldlineinc.com>
Maintainer-email: Matt Liss <matt@fieldlineindustries.com>
License-Expression: MIT
Project-URL: Homepage, https://fieldlineindustries.com
Project-URL: Documentation, https://pyflind.readthedocs.io/en/latest/
Project-URL: Repository, https://bitbucket.org/fl-industries/fli-python-oss
Keywords: FieldLine,sm200,sm300,smx00
Classifier: Programming Language :: Python :: 3
Classifier: Operating System :: OS Independent
Requires-Python: >=3.8
License-File: LICENSE
Requires-Dist: numpy
Requires-Dist: pyserial
Dynamic: license-file
